[
  {
    "id": "My-mans-smartphone",
    "titre": "My Man's Smartphone",
    "slug": "My-mans-smartphone",
    "categories": "Short Drama Vertical",
    "themes": "Romance, Comédie, Moderne",
    "pitch": "Découvrez le quotidien d'un couple à travers l'écran de leur smartphone.",
    "resume": "My Man's Smartphone est un short drama vertical qui explore les relations modernes à travers les conversations, photos et moments capturés sur un smartphone. Chaque épisode dévoile une facette différente de la vie de couple dans notre ère numérique.",
    "anneeProduction": "2024",
    "anneeDiffusion": "2024",
    "detenteursDroits": "KYOOL, Independance Prod",
    "realisateur": "À définir",
    "casting": "À définir",
    "producteur": "Independance Prod",
    "scenariste": "À définir",
    "categoriesPublic": "Tous publics",
    "hashtags": ["shortdrama", "vertical", "smartphone", "romance"],
    "motsCles": "romance, comédie, smartphone, couple, quotidien",
    "bandeAnnonce": "https://www.youtube.com/@KoreanFrenchTeleVision",
    "reseauxSociaux": {
      "youtube": "https://www.youtube.com/@KoreanFrenchTeleVision"
    },
    "images": [
      "image_1920x720.jpg",
      "image_1500x2100.jpg",
      "image_1080x1080.jpg"
    ]
  }
]
